README.txt
ez_setup.py
setup.py
whs.utils.flask.egg-info/PKG-INFO
whs.utils.flask.egg-info/SOURCES.txt
whs.utils.flask.egg-info/dependency_links.txt
whs.utils.flask.egg-info/namespace_packages.txt
whs.utils.flask.egg-info/requires.txt
whs.utils.flask.egg-info/top_level.txt
whs/utils/flask/__init__.py
whs/utils/flask/flask_utils.py
whs/utils/flask/resources.py